networkx_temporal/__init__.py
networkx_temporal/__version__.py
networkx_temporal/algorithms/__init__.py
networkx_temporal/algorithms/graph/__init__.py
networkx_temporal/algorithms/graph/centralization.py
networkx_temporal/algorithms/graph/conductance.py
networkx_temporal/algorithms/graph/modularity.py
networkx_temporal/algorithms/graph/modularity_multislice.py
networkx_temporal/algorithms/graph/modularity_spectral.py
networkx_temporal/algorithms/node/__init__.py
networkx_temporal/algorithms/node/bridging.py
networkx_temporal/algorithms/node/brokering.py
networkx_temporal/algorithms/node/degree.py
networkx_temporal/classes/__init__.py
networkx_temporal/classes/abc.py
networkx_temporal/classes/digraph.py
networkx_temporal/classes/factory.py
networkx_temporal/classes/functions.py
networkx_temporal/classes/graph.py
networkx_temporal/classes/multidigraph.py
networkx_temporal/classes/multigraph.py
networkx_temporal/classes/slice.py
networkx_temporal/classes/types.py
networkx_temporal/classes/wraps.py
networkx_temporal/drawing/__init__.py
networkx_temporal/drawing/draw.py
networkx_temporal/drawing/layout.py
networkx_temporal/drawing/networkx.py
networkx_temporal/generators/__init__.py
networkx_temporal/generators/examples.py
networkx_temporal/generators/generators.py
networkx_temporal/generators/sbm.py
networkx_temporal/generators/datasets/__init__.py
networkx_temporal/generators/datasets/collegemsg.py
networkx_temporal/generators/datasets/pubmed.py
networkx_temporal/readwrite/__init__.py
networkx_temporal/readwrite/reader.py
networkx_temporal/readwrite/readwrite.py
networkx_temporal/readwrite/writer.py
networkx_temporal/transform/__init__.py
networkx_temporal/transform/events.py
networkx_temporal/transform/snapshots.py
networkx_temporal/transform/static.py
networkx_temporal/transform/unrolled.py
networkx_temporal/typing/__init__.py
networkx_temporal/typing/typing.py
networkx_temporal/utils/__init__.py
networkx_temporal/utils/utils.py
networkx_temporal-1.3.0.dist-info/licenses/LICENSE.md
networkx_temporal-1.3.0.dist-info/METADATA
networkx_temporal-1.3.0.dist-info/WHEEL
networkx_temporal-1.3.0.dist-info/top_level.txt
networkx_temporal-1.3.0.dist-info/RECORD
