Metadata-Version: 2.4
Name: networkx-temporal
Version: 1.3.0
Summary: Python package to build and manipulate dynamic NetworkX graphs.
Author-email: Nelson Aloysio Reis de Almeida Passos <nelson.reis@phd.unipi.it>
Project-URL: Homepage, https://pypi.org/p/networkx-temporal/
Project-URL: Documentation, https://networkx-temporal.readthedocs.readwrite
Project-URL: Repository, https://github.com/nelsonaloysio/networkx-temporal
Project-URL: Issues, https://github.com/nelsonaloysio/networkx-temporal/issues
Project-URL: Changelog, https://github.com/nelsonaloysio/networkx-temporal/blob/main/CHANGELOG.md
Keywords: Network,Graph,Dynamic Graph,Temporal Network
Classifier: Development Status :: 5 - Production/Stable
Classifier: Intended Audience :: Developers
Classifier: Intended Audience :: Information Technology
Classifier: License :: OSI Approved :: BSD License
Classifier: Programming Language :: Python :: 3
Classifier: Topic :: Scientific/Engineering :: Information Analysis
Classifier: Topic :: Software Development :: Libraries :: Python Modules
Requires-Python: >=3.7
License-File: LICENSE.md
Requires-Dist: networkx>=2.1
Requires-Dist: numpy>=1.17.3
Requires-Dist: pandas>=1.1.0
Requires-Dist: scipy>=1.7.3
Provides-Extra: all
Requires-Dist: dgl; extra == "all"
Requires-Dist: dynetx; extra == "all"
Requires-Dist: graph-tool; extra == "all"
Requires-Dist: leidenalg; extra == "all"
Requires-Dist: matplotlib; extra == "all"
Requires-Dist: networkit; extra == "all"
Requires-Dist: python-igraph; extra == "all"
Requires-Dist: snap-stanford; extra == "all"
Requires-Dist: stellargraph; extra == "all"
Requires-Dist: teneto; extra == "all"
Requires-Dist: torch_geometric; extra == "all"
Provides-Extra: docs
Requires-Dist: sphinx-autodoc-typehints>=1.23.0; extra == "docs"
Requires-Dist: sphinx-rtd-theme>=2.0.0; extra == "docs"
Requires-Dist: sphinxemoji>=0.2.0; extra == "docs"
Provides-Extra: draw
Requires-Dist: matplotlib; extra == "draw"
Provides-Extra: ipynb
Requires-Dist: ipykernel; extra == "ipynb"
Requires-Dist: leidenalg; extra == "ipynb"
Requires-Dist: matplotlib; extra == "ipynb"
Requires-Dist: python-igraph; extra == "ipynb"
Dynamic: license-file
